README.md
setup.py
zware_api/__init__.py
zware_api/const.py
zware_api/lock.py
zware_api/objects.py
zware_api/zware.py
zware_api.egg-info/PKG-INFO
zware_api.egg-info/SOURCES.txt
zware_api.egg-info/dependency_links.txt
zware_api.egg-info/top_level.txt
zware_api/interfaces/__init__.py
zware_api/interfaces/alarm.py
zware_api/interfaces/base.py
zware_api/interfaces/battery.py
zware_api/interfaces/doorlock.py
zware_api/interfaces/usercode.py